binary_rw/__init__.py
binary_rw/binary_rw.py
binary_rw-1.0.3.dist-info/LICENSE
binary_rw-1.0.3.dist-info/METADATA
binary_rw-1.0.3.dist-info/WHEEL
binary_rw-1.0.3.dist-info/top_level.txt
binary_rw-1.0.3.dist-info/RECORD
