Metadata-Version: 2.1
Name: binary-rw
Version: 1.0.3
Summary: Simple library for reading binary files.
Home-page: https://gitlab.com/fkwilczek/binary-rw
Author: Filip K
Author-email: fkwilczek@gmail.com
License: GNU General Public License v3 (GPLv3)
Platform: UNKNOWN
Classifier: Programming Language :: Python :: 3
Classifier: Operating System :: OS Independent
Classifier: License :: OSI Approved :: GNU General Public License v3 (GPLv3)
License-File: LICENSE
